aiochan/__init__.py
aiochan/_util.py
aiochan/buffers.py
aiochan/channel.py
aiochan/test/__init__.py
aiochan/test/test_buffer.py
aiochan/test/test_channel.py
aiochan-0.2.7.dist-info/LICENSE
aiochan-0.2.7.dist-info/METADATA
aiochan-0.2.7.dist-info/WHEEL
aiochan-0.2.7.dist-info/top_level.txt
aiochan-0.2.7.dist-info/RECORD
