Metadata-Version: 2.1
Name: aiochan
Version: 0.2.7
Summary: CSP-style concurrency for Python
Home-page: https://github.com/zh217/aiochan
Author: Ziyang Hu
Author-email: hu.ziyang@cantab.net
License: Apache
Platform: any
Classifier: Development Status :: 4 - Beta
Classifier: License :: OSI Approved :: Apache Software License
Classifier: Programming Language :: Python :: 3.5
Classifier: Programming Language :: Python :: 3.6
Classifier: Programming Language :: Python :: 3.7
Classifier: Programming Language :: Python :: 3.8
Classifier: Programming Language :: Python :: 3.9
Classifier: Programming Language :: Python :: 3.10
Requires-Python: >=3.5.3
License-File: LICENSE
